cyprint/__init__.py
cyprint/cypb.py
cyprint/cyprint.py
cyprint-1.1.2.dist-info/METADATA
cyprint-1.1.2.dist-info/WHEEL
cyprint-1.1.2.dist-info/top_level.txt
cyprint-1.1.2.dist-info/RECORD
