Metadata-Version: 2.1
Name: cyprint
Version: 1.1.2
Summary: Customized colorful logging in Python
Home-page: https://pypi.org/manage/project/cyprint
Author: xciny
Author-email: 229735037@qq.com
License: MIT
Classifier: Programming Language :: Python :: 3
Classifier: License :: OSI Approved :: MIT License
Classifier: Operating System :: OS Independent
Requires-Dist: colorama
